{"_type":"export","__export_format":4,"__export_date":"2020-03-09T19:00:10.608Z","__export_source":"insomnia.desktop.app:v7.1.1","resources":[{"_id":"req_ccfaeab2b96747b08f779fc05d1cf5b6","authentication":{},"body":{},"created":1579019161082,"description":"","headers":[],"isPrivate":false,"metaSortKey":-1579019161082,"method":"GET","modified":1579095615426,"name":"Listar usuários","parameters":[],"parentId":"wrk_9cd1ccb54c104c6ea3d4fa77cf6832ea","settingDisableRenderRequestBody":false,"settingEncodeUrl":true,"settingFollowRedirects":"global","settingRebuildPath":true,"settingSendCookies":true,"settingStoreCookies":true,"url":"http://localhost:3333/","_type":"request"},{"_id":"wrk_9cd1ccb54c104c6ea3d4fa77cf6832ea","created":1579019100345,"description":"","modified":1579019100345,"name":"Insomnia","parentId":null,"_type":"workspace"},{"_id":"req_c91ab70aa681493494ac8dec683594ae","authentication":{},"body":{"mimeType":"application/json","text":"{\n\t\"name\": \"Tiago Marinho\",\n\t\"email\": \"tiago.marinho.797@gmail.com\",\n\t\"password\": \"123456789\"\n}"},"created":1581462307819,"description":"","headers":[{"id":"pair_db353699f20742cbb3a971ad706761c6","name":"Content-Type","value":"application/json"}],"isPrivate":false,"metaSortKey":-1581462307819,"method":"POST","modified":1582636949871,"name":"Create","parameters":[],"parentId":"fld_773c749003704ed0a592b9acf17175d7","settingDisableRenderRequestBody":false,"settingEncodeUrl":true,"settingFollowRedirects":"global","settingRebuildPath":true,"settingSendCookies":true,"settingStoreCookies":true,"url":"{{ base_url  }}/users","_type":"request"},{"_id":"fld_773c749003704ed0a592b9acf17175d7","created":1581462178438,"description":"","environment":{},"environmentPropertyOrder":null,"metaSortKey":-1581462178438,"modified":1581462178438,"name":"Users","parentId":"wrk_f3258507048141a08dacdad8aef05d4d","_type":"request_group"},{"_id":"wrk_f3258507048141a08dacdad8aef05d4d","created":1581462174833,"description":"","modified":1581462174833,"name":"GoBarber","parentId":null,"_type":"workspace"},{"_id":"req_73bb2bfb690d473c8908fc2d7e732031","authentication":{"token":"{{ token  }}","type":"bearer"},"body":{"mimeType":"application/json","text":"{\n\t\"name\": \"Tiaguetee\",\n\t\"email\": \"tlmmmmm@ic.u2fa2l.b2r\",\n\t\"oldPassword\": \"123456789\",\n\t\"password\": \"123456789\",\n\t\"confirmPassword\": \"123456789\",\n\t\"avatar_id\": 1\n}"},"created":1581466810458,"description":"","headers":[{"id":"pair_db353699f20742cbb3a971ad706761c6","name":"Content-Type","value":"application/json"}],"isPrivate":false,"metaSortKey":-1581341449608.5,"method":"PUT","modified":1582636996587,"name":"Update","parameters":[],"parentId":"fld_773c749003704ed0a592b9acf17175d7","settingDisableRenderRequestBody":false,"settingEncodeUrl":true,"settingFollowRedirects":"global","settingRebuildPath":true,"settingSendCookies":true,"settingStoreCookies":true,"url":"{{ base_url  }}/users","_type":"request"},{"_id":"req_5cda1c8c11704c02bf5f48841991a26a","authentication":{},"body":{"mimeType":"application/json","text":"{\n\t\"email\": \"tiago.marinho.797@gmail.com\",\n\t\"password\": \"123456789\"\n}"},"created":1581465745957,"description":"","headers":[{"id":"pair_efa0f1f2596640d6b08da52b6b6613fd","name":"Content-Type","value":"application/json"}],"isPrivate":false,"metaSortKey":-1581465745957,"method":"POST","modified":1583431565641,"name":"Create","parameters":[],"parentId":"fld_77b2d9fe15714d2d96283de81184de0a","settingDisableRenderRequestBody":false,"settingEncodeUrl":true,"settingFollowRedirects":"global","settingRebuildPath":true,"settingSendCookies":true,"settingStoreCookies":true,"url":"{{ base_url  }}/sessions","_type":"request"},{"_id":"fld_77b2d9fe15714d2d96283de81184de0a","created":1581465741352,"description":"","environment":{},"environmentPropertyOrder":null,"metaSortKey":-1581465741352,"modified":1581465741352,"name":"Sessions","parentId":"wrk_f3258507048141a08dacdad8aef05d4d","_type":"request_group"},{"_id":"req_83c3376784c2497eb736aa6547a1b20e","authentication":{"token":"{{ token  }}","type":"bearer"},"body":{"mimeType":"multipart/form-data","params":[{"description":"","fileName":"/home/tiago/UtilTiago/TCC/Images/SteamRecommender.png","id":"pair_6b67e52191ac434eb30df62cd4f1f1b7","name":"file","type":"file","value":""}]},"created":1582591455335,"description":"","headers":[{"id":"pair_058174dea10a4f74b1cac4532c7744d1","name":"Content-Type","value":"multipart/form-data"}],"isPrivate":false,"metaSortKey":-1582591455335,"method":"POST","modified":1583431605881,"name":"Create","parameters":[],"parentId":"fld_5b1a7af70f324851967278e887f3bc7f","settingDisableRenderRequestBody":false,"settingEncodeUrl":true,"settingFollowRedirects":"global","settingRebuildPath":true,"settingSendCookies":true,"settingStoreCookies":true,"url":"{{ base_url  }}/files","_type":"request"},{"_id":"fld_5b1a7af70f324851967278e887f3bc7f","created":1582591451375,"description":"","environment":{},"environmentPropertyOrder":null,"metaSortKey":-1582591451375,"modified":1582591451375,"name":"Files","parentId":"wrk_f3258507048141a08dacdad8aef05d4d","_type":"request_group"},{"_id":"req_a765f3e6eeda4b7b81f20ef1fca59c10","authentication":{"token":"{{ token  }}","type":"bearer"},"body":{},"created":1582638119952,"description":"","headers":[],"isPrivate":false,"metaSortKey":-1582638119952,"method":"GET","modified":1582638138020,"name":"Index","parameters":[],"parentId":"fld_00b1caa291df4adc99c063ab1b573794","settingDisableRenderRequestBody":false,"settingEncodeUrl":true,"settingFollowRedirects":"global","settingRebuildPath":true,"settingSendCookies":true,"settingStoreCookies":true,"url":"{{ base_url  }}/providers","_type":"request"},{"_id":"fld_00b1caa291df4adc99c063ab1b573794","created":1582638115478,"description":"","environment":{},"environmentPropertyOrder":null,"metaSortKey":-1582638115478,"modified":1582638115478,"name":"Providers","parentId":"wrk_f3258507048141a08dacdad8aef05d4d","_type":"request_group"},{"_id":"req_2394ca15b02644aaa58ac71000da22b4","authentication":{"token":"{{ token  }}","type":"bearer"},"body":{"mimeType":"application/json","text":"{\n\t\"provider_id\": 2,\n\t\"date\": \"2020-08-02T18:00:00-05:00\"\n}"},"created":1583106777011,"description":"","headers":[{"id":"pair_d8d6991e151e4b71ac53c6978593d915","name":"Content-Type","value":"application/json"}],"isPrivate":false,"metaSortKey":-1583106777011,"method":"POST","modified":1583431631288,"name":"Create","parameters":[],"parentId":"fld_84f181c87953434fb6c4f9eba9e0993b","settingDisableRenderRequestBody":false,"settingEncodeUrl":true,"settingFollowRedirects":"global","settingRebuildPath":true,"settingSendCookies":true,"settingStoreCookies":true,"url":"{{ base_url  }}/appointments","_type":"request"},{"_id":"fld_84f181c87953434fb6c4f9eba9e0993b","created":1583106766821,"description":"","environment":{},"environmentPropertyOrder":null,"metaSortKey":-1583106766821,"modified":1583106766821,"name":"Appointments","parentId":"wrk_f3258507048141a08dacdad8aef05d4d","_type":"request_group"},{"_id":"req_fe631a6e9ced462fa10f12cc938919f4","authentication":{"token":"{{ token  }}","type":"bearer"},"body":{"mimeType":"application/json","text":"{\n\t\"provider_id\": 4,\n\t\"date\": \"2020-08-01T18:00:00-03:00\"\n}"},"created":1583109177721,"description":"","headers":[{"id":"pair_d8d6991e151e4b71ac53c6978593d915","name":"Content-Type","value":"application/json"}],"isPrivate":false,"metaSortKey":-1582872448481.5,"method":"GET","modified":1583431617132,"name":"List","parameters":[{"description":"","id":"pair_883b08bb6e314f0fac1d611e06563910","name":"page","value":"1"}],"parentId":"fld_84f181c87953434fb6c4f9eba9e0993b","settingDisableRenderRequestBody":false,"settingEncodeUrl":true,"settingFollowRedirects":"global","settingRebuildPath":true,"settingSendCookies":true,"settingStoreCookies":true,"url":"{{ base_url  }}/appointments","_type":"request"},{"_id":"req_e39c29d3bfd044e483508c7f56e7c552","authentication":{"token":"{{ token  }}","type":"bearer"},"body":{},"created":1583433163323,"description":"","headers":[],"isPrivate":false,"metaSortKey":-1583433163323,"method":"DELETE","modified":1583433188263,"name":"Delete","parameters":[],"parentId":"fld_84f181c87953434fb6c4f9eba9e0993b","settingDisableRenderRequestBody":false,"settingEncodeUrl":true,"settingFollowRedirects":"global","settingRebuildPath":true,"settingSendCookies":true,"settingStoreCookies":true,"url":"{{ base_url  }}/appointments/1","_type":"request"},{"_id":"req_4e4bb496c5064140af724304785c972d","authentication":{"token":"{{ token  }}","type":"bearer"},"body":{"mimeType":"application/json","text":""},"created":1583110366851,"description":"","headers":[{"id":"pair_82c1c432a4e54686abd62e0a795be56b","name":"Content-Type","value":"application/json"}],"isPrivate":false,"metaSortKey":-1583110366851,"method":"GET","modified":1583110681833,"name":"List","parameters":[{"description":"","id":"pair_9cf33133890840c7aca6b65c0fe988ad","name":"date","value":"2020-08-01T00:00:00-03:00"}],"parentId":"fld_471d8a4c68e040f39f631f9de87ccbe7","settingDisableRenderRequestBody":false,"settingEncodeUrl":true,"settingFollowRedirects":"global","settingRebuildPath":true,"settingSendCookies":true,"settingStoreCookies":true,"url":"{{ base_url  }}/schedule","_type":"request"},{"_id":"fld_471d8a4c68e040f39f631f9de87ccbe7","created":1583110357261,"description":"","environment":{},"environmentPropertyOrder":null,"metaSortKey":-1583106766871,"modified":1583110363315,"name":"Schedule","parentId":"wrk_f3258507048141a08dacdad8aef05d4d","_type":"request_group"},{"_id":"req_f169f1feddfc4ed19f8fe24d176aed65","authentication":{"token":"{{ token  }}","type":"bearer"},"body":{},"created":1583365028278,"description":"","headers":[],"isPrivate":false,"metaSortKey":-1583365028278,"method":"GET","modified":1583365047242,"name":"List","parameters":[],"parentId":"fld_4dcf58f99a3649ecbc95d94310e9738a","settingDisableRenderRequestBody":false,"settingEncodeUrl":true,"settingFollowRedirects":"global","settingRebuildPath":true,"settingSendCookies":true,"settingStoreCookies":true,"url":"{{ base_url  }}/notifications","_type":"request"},{"_id":"fld_4dcf58f99a3649ecbc95d94310e9738a","created":1583365025032,"description":"","environment":{},"environmentPropertyOrder":null,"metaSortKey":-1583365025032,"modified":1583365025032,"name":"Notifications","parentId":"wrk_f3258507048141a08dacdad8aef05d4d","_type":"request_group"},{"_id":"req_73e1c295528e4ede852c84cd84235f49","authentication":{"token":"{{ token  }}","type":"bearer"},"body":{},"created":1583366183052,"description":"","headers":[],"isPrivate":false,"metaSortKey":-1583366183052,"method":"PUT","modified":1583366236491,"name":"Update","parameters":[],"parentId":"fld_4dcf58f99a3649ecbc95d94310e9738a","settingDisableRenderRequestBody":false,"settingEncodeUrl":true,"settingFollowRedirects":"global","settingRebuildPath":true,"settingSendCookies":true,"settingStoreCookies":true,"url":"{{ base_url  }}/notifications/5e603dbf876e8a32ee4132ec","_type":"request"},{"_id":"req_c3c7ac9f3ff84090b50bdc066ec0009a","authentication":{},"body":{"mimeType":"application/json","text":"{\n\t\"name\": \"Tiago Marinho\",\n\t\"email\": \"tiago.marinho.797@gmail.com\",\n\t\"password\": \"123456789\"\n}"},"created":1583761768846,"description":"","headers":[{"id":"pair_d31f66a4ef644c149aeffc40f43e5813","name":"Content-Type","value":"application/json"}],"isPrivate":false,"metaSortKey":-1583761768846,"method":"POST","modified":1583761976271,"name":"Create","parameters":[],"parentId":"fld_8c5e200aa25045588f228fbd1cecae67","settingDisableRenderRequestBody":false,"settingEncodeUrl":true,"settingFollowRedirects":"global","settingRebuildPath":true,"settingSendCookies":true,"settingStoreCookies":true,"url":"{{ base_url  }}/users","_type":"request"},{"_id":"fld_8c5e200aa25045588f228fbd1cecae67","created":1583761762861,"description":"","environment":{},"environmentPropertyOrder":null,"metaSortKey":-1583761762861,"modified":1583761762861,"name":"Users","parentId":"wrk_330933dafdae4ea5a03e6a131828538c","_type":"request_group"},{"_id":"wrk_330933dafdae4ea5a03e6a131828538c","created":1583761737545,"description":"","modified":1583761737545,"name":"FastFeet","parentId":null,"_type":"workspace"},{"_id":"req_325d2eb4465f436dafae592965b7cc94","authentication":{"token":"{{ token  }}","type":"bearer"},"body":{},"created":1583764364529,"description":"","headers":[],"isPrivate":false,"metaSortKey":-1583764364529,"method":"GET","modified":1583764513890,"name":"List","parameters":[],"parentId":"fld_8c5e200aa25045588f228fbd1cecae67","settingDisableRenderRequestBody":false,"settingEncodeUrl":true,"settingFollowRedirects":"global","settingRebuildPath":true,"settingSendCookies":true,"settingStoreCookies":true,"url":"{{ base_url  }}/users","_type":"request"},{"_id":"req_c86419989a1b4a2f95653d3ba26471bd","authentication":{"token":"{{ token  }}","type":"bearer"},"body":{"mimeType":"application/json","text":"{\n\t\"name\": \"Tiago Marinho\",\n\t\"email\": \"tiago.marinho.797@gmail.com\",\n\t\"oldPassword\": \"123456789\",\n\t\"password\": \"123456\",\n\t\"confirmPassword\": \"123456\"\n}"},"created":1583765214297,"description":"","headers":[{"id":"pair_e9a335fd884743b4846713c8c3054275","name":"Content-Type","value":"application/json"}],"isPrivate":false,"metaSortKey":-1583765214297,"method":"PUT","modified":1583765280594,"name":"Update","parameters":[],"parentId":"fld_8c5e200aa25045588f228fbd1cecae67","settingDisableRenderRequestBody":false,"settingEncodeUrl":true,"settingFollowRedirects":"global","settingRebuildPath":true,"settingSendCookies":true,"settingStoreCookies":true,"url":"{{ base_url  }}/users","_type":"request"},{"_id":"req_be83562ee5804724bb487f53957c0312","authentication":{},"body":{"mimeType":"application/json","text":"{\n\t\"email\": \"admin@fastfeet.com\",\n\t\"password\": \"123456\"\n}"},"created":1583764430822,"description":"","headers":[{"id":"pair_86cda2e6d491412199917e6826395972","name":"Content-Type","value":"application/json"}],"isPrivate":false,"metaSortKey":-1583764430822,"method":"POST","modified":1583766265295,"name":"Create","parameters":[],"parentId":"fld_b6d8ff23d6c14ec28d928c7194b82afa","settingDisableRenderRequestBody":false,"settingEncodeUrl":true,"settingFollowRedirects":"global","settingRebuildPath":true,"settingSendCookies":true,"settingStoreCookies":true,"url":"{{ base_url  }}/sessions","_type":"request"},{"_id":"fld_b6d8ff23d6c14ec28d928c7194b82afa","created":1583764412951,"description":"","environment":{},"environmentPropertyOrder":null,"metaSortKey":-1583764412951,"modified":1583764412951,"name":"Sessions","parentId":"wrk_330933dafdae4ea5a03e6a131828538c","_type":"request_group"},{"_id":"req_e2c8973e1f834f88809497b3d8e0facf","authentication":{"token":"{{ token  }}","type":"bearer"},"body":{"mimeType":"application/json","text":""},"created":1583765544309,"description":"","headers":[{"name":"Content-Type","value":"application/json"}],"isPrivate":false,"metaSortKey":-1583765544309,"method":"POST","modified":1583765591397,"name":"Create","parameters":[],"parentId":"fld_1967b2858f6c4758a3e2a41ff4e56a68","settingDisableRenderRequestBody":false,"settingEncodeUrl":true,"settingFollowRedirects":"global","settingRebuildPath":true,"settingSendCookies":true,"settingStoreCookies":true,"url":"{{ base_url  }}/recipients","_type":"request"},{"_id":"fld_1967b2858f6c4758a3e2a41ff4e56a68","created":1583765511397,"description":"","environment":{},"environmentPropertyOrder":null,"metaSortKey":-1583765511397,"modified":1583765511397,"name":"Recipients","parentId":"wrk_330933dafdae4ea5a03e6a131828538c","_type":"request_group"},{"_id":"req_335da0ddbad545dc98ff4d0a6501fee5","authentication":{"token":"{{ token  }}","type":"bearer"},"body":{},"created":1583765558700,"description":"","headers":[],"isPrivate":false,"metaSortKey":-1583765558700,"method":"GET","modified":1583765585387,"name":"Update","parameters":[],"parentId":"fld_1967b2858f6c4758a3e2a41ff4e56a68","settingDisableRenderRequestBody":false,"settingEncodeUrl":true,"settingFollowRedirects":"global","settingRebuildPath":true,"settingSendCookies":true,"settingStoreCookies":true,"url":"{{ base_url  }}/recipients","_type":"request"},{"_id":"env_f6a0f39ab57694c3b2e91cbd19c2a1d30d62b3e2","color":null,"created":1579019100377,"data":{},"dataPropertyOrder":null,"isPrivate":false,"metaSortKey":1579019100377,"modified":1579019100377,"name":"Base Environment","parentId":"wrk_9cd1ccb54c104c6ea3d4fa77cf6832ea","_type":"environment"},{"_id":"jar_f6a0f39ab57694c3b2e91cbd19c2a1d30d62b3e2","cookies":[],"created":1579019100379,"modified":1579019100379,"name":"Default Jar","parentId":"wrk_9cd1ccb54c104c6ea3d4fa77cf6832ea","_type":"cookie_jar"},{"_id":"env_1a24b648632bd34d68c7aa9bb2836d6ed49f3290","color":null,"created":1581462174880,"data":{"base_url":"http://localhost:3333","token":"eyJhbGciOiJIUzI1NiIsInR5cCI6IkpXVCJ9.eyJpZCI6MSwiaWF0IjoxNTgzNDMxNTY3LCJleHAiOjE1ODQwMzYzNjd9.Ckn6Tbxc9oWFm8z606vWorkCHx_DbWKI4LtuzASGPtk"},"dataPropertyOrder":{"&":["base_url","token"]},"isPrivate":false,"metaSortKey":1581462174880,"modified":1583431579112,"name":"Base Environment","parentId":"wrk_f3258507048141a08dacdad8aef05d4d","_type":"environment"},{"_id":"jar_1a24b648632bd34d68c7aa9bb2836d6ed49f3290","cookies":[],"created":1581462174886,"modified":1582636778316,"name":"Default Jar","parentId":"wrk_f3258507048141a08dacdad8aef05d4d","_type":"cookie_jar"},{"_id":"env_b8281595e29487bd43c8f68f7a1a4130a0ec43a4","color":null,"created":1583761737682,"data":{"base_url":"http://localhost:3333","token":"eyJhbGciOiJIUzI1NiIsInR5cCI6IkpXVCJ9.eyJpZCI6MiwicHJvdmlkZXIiOnRydWUsImlhdCI6MTU4Mzc2NjI2NiwiZXhwIjoxNTg0MzcxMDY2fQ.4x_7WI8IRcdsxD-4wPKfP9R3CIZ_ZgW7mh6nkIUTz34"},"dataPropertyOrder":{"&":["base_url","token"]},"isPrivate":false,"metaSortKey":1583761737682,"modified":1583766287009,"name":"Base Environment","parentId":"wrk_330933dafdae4ea5a03e6a131828538c","_type":"environment"},{"_id":"jar_b8281595e29487bd43c8f68f7a1a4130a0ec43a4","cookies":[],"created":1583761737689,"modified":1583761737689,"name":"Default Jar","parentId":"wrk_330933dafdae4ea5a03e6a131828538c","_type":"cookie_jar"}]}